craft_mol/__init__.py
craft_mol/batch_feature.py
craft_mol/fine_tune_without_pretrain.py
craft_mol/finetune.py
craft_mol/finetune_retrieval.py
craft_mol/interact.py
craft_mol/molecular_weights.py
craft_mol/pretrain.py
craft_mol/smiles_iupac.py
craft_mol/data/Mol-Instructions/Mol-Instructions.py
craft_mol/data/Mol-Instructions/load_dataset_local.py
craft_mol/data/Mol-Instructions/merge_data.py
craft_mol/data/Mol-Instructions/mol_instructions_parr.py
craft_mol/data/Mol-Instructions/process_json.py
craft_mol/data/Mol-Instructions/test.py
craft_mol/data/pubchem324k/continue_unfinished.py
craft_mol/data/pubchem324k/handle_unfinished.py
craft_mol/data/pubchem324k/merge_data.py
craft_mol/data/pubchem324k/parall_pubchem324k.py
craft_mol/data/pubchem324k/pubchem324k.py
craft_mol/data/pubchem324k/test.py
craft_mol/dataset/__init__.py
craft_mol/dataset/atom_rep.py
craft_mol/dataset/data.py
craft_mol/dataset/data4csv.py
craft_mol/dataset/data4json.py
craft_mol/dataset/tokenizer.py
craft_mol/model/TMMF.py
craft_mol/model/__init__.py
craft_mol/model/bert.py
craft_mol/model/gnn.py
craft_mol/optim/__init__.py
craft_mol/optim/adafactor.py
craft_mol/optim/adahessian.py
craft_mol/optim/adamp.py
craft_mol/optim/adamw.py
craft_mol/optim/lookahead.py
craft_mol/optim/nadam.py
craft_mol/optim/novograd.py
craft_mol/optim/nvnovograd.py
craft_mol/optim/optim_factory.py
craft_mol/optim/radam.py
craft_mol/optim/rmsprop_tf.py
craft_mol/optim/sgdp.py
craft_mol/scheduler/__init__.py
craft_mol/scheduler/cosine_lr.py
craft_mol/scheduler/plateau_lr.py
craft_mol/scheduler/scheduler.py
craft_mol/scheduler/scheduler_factory.py
craft_mol/scheduler/step_lr.py
craft_mol/scheduler/tanh_lr.py
craft_mol/utils/__init__.py
craft_mol/utils/convert_json.py
craft_mol/utils/utils.py
model_weights/single_feature.py
model_weights/test.py
craft_mol-1.5.1.dist-info/LICENSE
craft_mol-1.5.1.dist-info/METADATA
craft_mol-1.5.1.dist-info/WHEEL
craft_mol-1.5.1.dist-info/top_level.txt
craft_mol-1.5.1.dist-info/RECORD
