Metadata-Version: 2.2
Name: craft-mol
Version: 1.5.1
Summary: CRAFT: Consistent Representational Fusion of Three Molecular Modalities.
License:                                  Apache License
Classifier: Programming Language :: Python :: 3
Classifier: License :: OSI Approved :: Apache Software License
Requires-Python: >=3.10
License-File: LICENSE
Requires-Dist: torch==2.5.1
Requires-Dist: torch-scatter==2.1.2
Requires-Dist: torch-geometric==2.6.1
Requires-Dist: selfies==2.2.0
Requires-Dist: ruamel.yaml==0.16.6
Requires-Dist: tqdm==4.67.1
Requires-Dist: toolz==1.0.0
